{
  "publish": true,
  "hide": null,
  "pinned": null,
  "title": "Errors in shell scripts",
  "id": "e410736b-4d6a-4a1d-b5c0-26cb0451cf45",
  "related": null,
  "update": "2025-01-30",
  "date": "2016-06-27",
  "authors": [
    "Boris Buliga"
  ],
  "description": "A practical guide on error handling in shell scripts, focusing on the use of set -e (exit-on-error mode) and trap commands to manage failures and cleanup operations, with clear examples demonstrating how to write more robust shell scripts.",
  "tags": [
    "shell"
  ]
}
